code/__init__.py
tits-0.2.0.dist-info/licenses/LICENSE.txt
tits-0.2.0.dist-info/METADATA
tits-0.2.0.dist-info/WHEEL
tits-0.2.0.dist-info/top_level.txt
tits-0.2.0.dist-info/RECORD
