Metadata-Version: 2.4
Name: tits
Version: 0.2.0
Summary: مكتبة بايثون لتسهيل الفحص وغيره
Home-page: https://hso1.netlify.app
Author: حسو ال علي
Author-email: lyhasneen70@gmail.com
Classifier: Programming Language :: Python :: 3
Classifier: License :: OSI Approved :: MIT License
Classifier: Operating System :: OS Independent
Requires-Python: >=3.8
License-File: LICENSE.txt
Requires-Dist: requests
Requires-Dist: user_agent
Dynamic: author
Dynamic: author-email
Dynamic: classifier
Dynamic: description
Dynamic: description-content-type
Dynamic: home-page
Dynamic: license-file
Dynamic: requires-dist
Dynamic: requires-python
Dynamic: summary
